API/app/__init__.py
API/app/main.py
simplonbd/__init__.py
simplonbd/crud_dai.py
simplonbd/models.py
simplonbd-0.1.0.dist-info/METADATA
simplonbd-0.1.0.dist-info/WHEEL
simplonbd-0.1.0.dist-info/top_level.txt
simplonbd-0.1.0.dist-info/RECORD
