Metadata-Version: 2.1
Name: simplonbd
Version: 0.1.0
Summary: package to integrate bdd simplon
Author: dai
Author-email: dai.tensaout@gmail.com
Classifier: Programming Language :: Python :: 3
Classifier: License :: OSI Approved :: MIT License
Classifier: Operating System :: OS Independent
Requires-Python: >=3.6
